chungking/__init__.py
chungking/api.py
chungking/main.py
chungking/storage.py
chungking-0.1.0.dist-info/licenses/LICENSE
chungking-0.1.0.dist-info/METADATA
chungking-0.1.0.dist-info/WHEEL
chungking-0.1.0.dist-info/top_level.txt
chungking-0.1.0.dist-info/RECORD
