Metadata-Version: 2.4
Name: chungking
Version: 0.1.0
Summary: 基于Firecrawl设计的通用网页爬取API服务
Author-email: Your Name <your.email@example.com>
Classifier: Programming Language :: Python :: 3
Classifier: License :: OSI Approved :: MIT License
Classifier: Operating System :: OS Independent
Requires-Python: >=3.8
License-File: LICENSE
Requires-Dist: fastapi>=0.68.0
Requires-Dist: uvicorn>=0.15.0
Requires-Dist: pydantic>=1.8.2
Requires-Dist: playwright>=1.30.0
Requires-Dist: beautifulsoup4>=4.9.3
Requires-Dist: requests>=2.26.0
Requires-Dist: python-multipart>=0.0.5
Requires-Dist: python-dotenv>=1.0.0
Dynamic: license-file
